plummet/__init__.py
plummet-1.2.1.dist-info/LICENSE.md
plummet-1.2.1.dist-info/METADATA
plummet-1.2.1.dist-info/WHEEL
plummet-1.2.1.dist-info/RECORD
