Metadata-Version: 2.1
Name: plummet
Version: 1.2.1
Summary: Utilities for testing with pendulum timestamps
Home-page: https://github.com/dusktreader/plummet
License: MIT
Author: Tucker Beck
Author-email: tucker.beck@gmail.com
Requires-Python: >=3.8,<4.0
Classifier: License :: OSI Approved :: MIT License
Classifier: Programming Language :: Python :: 3
Classifier: Programming Language :: Python :: 3.8
Classifier: Programming Language :: Python :: 3.9
Classifier: Programming Language :: Python :: 3.10
Classifier: Programming Language :: Python :: 3.11
Provides-Extra: time-machine
Requires-Dist: pendulum (>=2)
Requires-Dist: py-buzz (>=3.1)
Requires-Dist: time-machine (>=2) ; extra == "time-machine"
Project-URL: Repository, https://github.com/dusktreader/plummet
